nonebot_plugin_no_repeat.py
nonebot_plugin_no_repeat-0.0.1.dist-info/LICENSE
nonebot_plugin_no_repeat-0.0.1.dist-info/METADATA
nonebot_plugin_no_repeat-0.0.1.dist-info/WHEEL
nonebot_plugin_no_repeat-0.0.1.dist-info/RECORD
