Metadata-Version: 2.1
Name: nonebot-plugin-no-repeat
Version: 0.0.1
Summary: 不要复读
Home-page: https://github.com/bridgeL/nonebot-plugin-no-repeat
License: MIT
Author: Su
Author-email: wxlxy316@163.com
Requires-Python: >=3.8,<4.0
Classifier: License :: OSI Approved :: MIT License
Classifier: Programming Language :: Python :: 3
Classifier: Programming Language :: Python :: 3.8
Classifier: Programming Language :: Python :: 3.9
Classifier: Programming Language :: Python :: 3.10
Classifier: Programming Language :: Python :: 3.11
Requires-Dist: nonebot2 (>=2.0.0b5,<3.0.0)
Project-URL: Repository, https://github.com/bridgeL/nonebot-plugin-no-repeat
